csv2cte/__init__.py
csv2cte/cli.py
csv2cte-0.1.2.dist-info/METADATA
csv2cte-0.1.2.dist-info/WHEEL
csv2cte-0.1.2.dist-info/entry_points.txt
csv2cte-0.1.2.dist-info/top_level.txt
csv2cte-0.1.2.dist-info/RECORD
