Metadata-Version: 2.4
Name: csv2cte
Version: 0.1.2
Summary: Convert CSV files to PostgreSQL VALUES‑based CTEs.
Author-email: Aric Showalter <aricshow@gmail.com>
License: MIT
Keywords: csv,sql,postgresql,cli
Classifier: Programming Language :: Python :: 3
Classifier: Programming Language :: Python :: 3 :: Only
Classifier: License :: OSI Approved :: MIT License
Classifier: Operating System :: OS Independent
Requires-Python: >=3.9
Requires-Dist: typer[all]>=0.12.0
Provides-Extra: dev
Requires-Dist: pytest>=7; extra == "dev"
Requires-Dist: black>=24; extra == "dev"
Requires-Dist: ruff>=0.6; extra == "dev"
